<?xml version="1.0" encoding="UTF-8" standalone="yes"?>
<items>
	<it>
		<idit>1</idit>
		<tid>0</tid>
		<name>sword</name>
		<s>2</s>
		<a>1</a>
		<e>1</e>
		<i>0</i>
		<ps>100</ps>
		<pa>0</pa>
		<pe>0</pe>
		<pi>0</pi>
	</it>
	<it>
		<idit>2</idit>
		<tid>1</tid>
		<name>helmet</name>
		<s>2</s>
		<a>1</a>
		<e>1</e>
		<i>0</i>
		<ps>0</ps>
		<pa>0</pa>
		<pe>0</pe>
		<pi>0</pi>
	</it>
	<it>
		<idit>3</idit>
		<tid>2</tid>
		<name>armour</name>
		<s>2</s>
		<a>1</a>
		<e>1</e>
		<i>0</i>
		<ps>0</ps>
		<pa>0</pa>
		<pe>0</pe>
		<pi>0</pi>
	</it>
	<it>
		<idit>4</idit>
		<tid>3</tid>
		<name>leggins</name>
		<s>2</s>
		<a>1</a>
		<e>1</e>
		<i>0</i>
		<ps>0</ps>
		<pa>0</pa>
		<pe>0</pe>
		<pi>0</pi>
	</it>
	<it>
		<idit>5</idit>
		<tid>4</tid>
		<name>boots</name>
		<s>2</s>
		<a>1</a>
		<e>1</e>
		<i>0</i>
		<ps>0</ps>
		<pa>0</pa>
		<pe>0</pe>
		<pi>0</pi>
	</it>
	<it>
		<idit>6</idit>
		<tid>5</tid>
		<name>shield</name>
		<s>2</s>
		<a>1</a>
		<e>1</e>
		<i>0</i>
		<ps>0</ps>
		<pa>0</pa>
		<pe>0</pe>
		<pi>0</pi>
	</it>
	<it>
		<idit>7</idit>
		<tid>6</tid>
		<name>dagger</name>
		<s>1</s>
		<a>3</a>
		<e>0</e>
		<i>0</i>
		<ps>40</ps>
		<pa>80</pa>
		<pe>0</pe>
		<pi>0</pi>
	</it>
	<it>
		<idit>8</idit>
		<tid>17</tid>
		<name>assasin hood</name>
		<s>1</s>
		<a>3</a>
		<e>0</e>
		<i>0</i>
		<ps>0</ps>
		<pa>0</pa>
		<pe>0</pe>
		<pi>0</pi>
	</it>
	<it>
		<idit>9</idit>
		<tid>18</tid>
		<name>assasin armour</name>
		<s>1</s>
		<a>3</a>
		<e>0</e>
		<i>0</i>
		<ps>0</ps>
		<pa>0</pa>
		<pe>0</pe>
		<pi>0</pi>
	</it>
	<it>
		<idit>10</idit>
		<tid>3</tid>
		<name>assasin leggins</name>
		<s>1</s>
		<a>3</a>
		<e>0</e>
		<i>0</i>
		<ps>0</ps>
		<pa>0</pa>
		<pe>0</pe>
		<pi>0</pi>
	</it>
	<it>
		<idit>11</idit>
		<tid>4</tid>
		<name>assasin boots</name>
		<s>1</s>
		<a>3</a>
		<e>0</e>
		<i>0</i>
		<ps>0</ps>
		<pa>0</pa>
		<pe>0</pe>
		<pi>0</pi>
	</it>
	<it>
		<idit>12</idit>
		<tid>5</tid>
		<name>sec. Dagger</name>
		<s>1</s>
		<a>3</a>
		<e>0</e>
		<i>0</i>
		<ps>0</ps>
		<pa>0</pa>
		<pe>0</pe>
		<pi>0</pi>
	</it>
	<it>
		<idit>13</idit>
		<tid>7</tid>
		<name>axe</name>
		<s>3</s>
		<a>1</a>
		<e>0</e>
		<i>0</i>
		<ps>110</ps>
		<pa>10</pa>
		<pe>0</pe>
		<pi>0</pi>
	</it>
	<it>
		<idit>14</idit>
		<tid>1</tid>
		<name>berserker helmet</name>
		<s>3</s>
		<a>1</a>
		<e>0</e>
		<i>0</i>
		<ps>0</ps>
		<pa>0</pa>
		<pe>0</pe>
		<pi>0</pi>
	</it>
	<it>
		<idit>15</idit>
		<tid>2</tid>
		<name>berserker armour</name>
		<s>3</s>
		<a>1</a>
		<e>0</e>
		<i>0</i>
		<ps>0</ps>
		<pa>0</pa>
		<pe>0</pe>
		<pi>0</pi>
	</it>
	<it>
		<idit>16</idit>
		<tid>3</tid>
		<name>berserker leggins</name>
		<s>3</s>
		<a>1</a>
		<e>0</e>
		<i>0</i>
		<ps>0</ps>
		<pa>0</pa>
		<pe>0</pe>
		<pi>0</pi>
	</it>
	<it>
		<idit>17</idit>
		<tid>4</tid>
		<name>berserker boots</name>
		<s>3</s>
		<a>1</a>
		<e>0</e>
		<i>0</i>
		<ps>0</ps>
		<pa>0</pa>
		<pe>0</pe>
		<pi>0</pi>
	</it>
	<it>
		<idit>18</idit>
		<tid>5</tid>
		<name>berserker shield</name>
		<s>3</s>
		<a>1</a>
		<e>0</e>
		<i>0</i>
		<ps>0</ps>
		<pa>0</pa>
		<pe>0</pe>
		<pi>0</pi>
	</it>
	<it>
		<idit>19</idit>
		<tid>8</tid>
		<name>spell thome</name>
		<s>0</s>
		<a>0</a>
		<e>1</e>
		<i>3</i>
		<ps>0</ps>
		<pa>0</pa>
		<pe>40</pe>
		<pi>80</pi>
	</it>
	<it>
		<idit>20</idit>
		<tid>1</tid>
		<name>enchanter hood</name>
		<s>0</s>
		<a>0</a>
		<e>1</e>
		<i>3</i>
		<ps>0</ps>
		<pa>0</pa>
		<pe>0</pe>
		<pi>0</pi>
	</it>
	<it>
		<idit>21</idit>
		<tid>2</tid>
		<name>enchanter robe</name>
		<s>0</s>
		<a>0</a>
		<e>1</e>
		<i>3</i>
		<ps>0</ps>
		<pa>0</pa>
		<pe>0</pe>
		<pi>0</pi>
	</it>
	<it>
		<idit>22</idit>
		<tid>3</tid>
		<name>enchanter leggins</name>
		<s>0</s>
		<a>0</a>
		<e>1</e>
		<i>3</i>
		<ps>0</ps>
		<pa>0</pa>
		<pe>0</pe>
		<pi>0</pi>
	</it>
	<it>
		<idit>23</idit>
		<tid>4</tid>
		<name>enchanter boots</name>
		<s>0</s>
		<a>0</a>
		<e>1</e>
		<i>3</i>
		<ps>0</ps>
		<pa>0</pa>
		<pe>0</pe>
		<pi>0</pi>
	</it>
	<it>
		<idit>24</idit>
		<tid>15</tid>
		<name>enchanter orb</name>
		<s>0</s>
		<a>0</a>
		<e>1</e>
		<i>3</i>
		<ps>0</ps>
		<pa>0</pa>
		<pe>0</pe>
		<pi>0</pi>
	</it>
	<it>
		<idit>25</idit>
		<tid>9</tid>
		<name>magic wand</name>
		<s>0</s>
		<a>1</a>
		<e>0</e>
		<i>3</i>
		<ps>0</ps>
		<pa>10</pa>
		<pe>0</pe>
		<pi>100</pi>
	</it>
	<it>
		<idit>26</idit>
		<tid>17</tid>
		<name>wizard hood</name>
		<s>0</s>
		<a>1</a>
		<e>0</e>
		<i>3</i>
		<ps>0</ps>
		<pa>0</pa>
		<pe>0</pe>
		<pi>0</pi>
	</it>
	<it>
		<idit>27</idit>
		<tid>18</tid>
		<name>wizard robe</name>
		<s>0</s>
		<a>1</a>
		<e>0</e>
		<i>3</i>
		<ps>0</ps>
		<pa>0</pa>
		<pe>0</pe>
		<pi>0</pi>
	</it>
	<it>
		<idit>28</idit>
		<tid>3</tid>
		<name>wizard leggins</name>
		<s>0</s>
		<a>1</a>
		<e>0</e>
		<i>3</i>
		<ps>0</ps>
		<pa>0</pa>
		<pe>0</pe>
		<pi>0</pi>
	</it>
	<it>
		<idit>29</idit>
		<tid>4</tid>
		<name>wizard boots</name>
		<s>0</s>
		<a>1</a>
		<e>0</e>
		<i>3</i>
		<ps>0</ps>
		<pa>0</pa>
		<pe>0</pe>
		<pi>0</pi>
	</it>
	<it>
		<idit>30</idit>
		<tid>15</tid>
		<name>wizard orb</name>
		<s>0</s>
		<a>1</a>
		<e>0</e>
		<i>3</i>
		<ps>0</ps>
		<pa>0</pa>
		<pe>0</pe>
		<pi>0</pi>
	</it>
	<it>
		<idit>31</idit>
		<tid>10</tid>
		<name>bow</name>
		<s>1</s>
		<a>2</a>
		<e>0</e>
		<i>1</i>
		<ps>20</ps>
		<pa>80</pa>
		<pe>10</pe>
		<pi>10</pi>
	</it>
	<it>
		<idit>32</idit>
		<tid>17</tid>
		<name>archer hood</name>
		<s>1</s>
		<a>2</a>
		<e>0</e>
		<i>1</i>
		<ps>0</ps>
		<pa>0</pa>
		<pe>0</pe>
		<pi>0</pi>
	</it>
	<it>
		<idit>33</idit>
		<tid>18</tid>
		<name>archer robe</name>
		<s>1</s>
		<a>2</a>
		<e>0</e>
		<i>1</i>
		<ps>0</ps>
		<pa>0</pa>
		<pe>0</pe>
		<pi>0</pi>
	</it>
	<it>
		<idit>34</idit>
		<tid>3</tid>
		<name>archer leggins</name>
		<s>1</s>
		<a>2</a>
		<e>0</e>
		<i>1</i>
		<ps>0</ps>
		<pa>0</pa>
		<pe>0</pe>
		<pi>0</pi>
	</it>
	<it>
		<idit>35</idit>
		<tid>4</tid>
		<name>archer boots</name>
		<s>1</s>
		<a>2</a>
		<e>0</e>
		<i>1</i>
		<ps>0</ps>
		<pa>0</pa>
		<pe>0</pe>
		<pi>0</pi>
	</it>
	<it>
		<idit>36</idit>
		<tid>16</tid>
		<name>archer glove</name>
		<s>1</s>
		<a>2</a>
		<e>0</e>
		<i>1</i>
		<ps>0</ps>
		<pa>0</pa>
		<pe>0</pe>
		<pi>0</pi>
	</it>
	<it>
		<idit>37</idit>
		<tid>11</tid>
		<name>mace</name>
		<s>2</s>
		<a>0</a>
		<e>2</e>
		<i>0</i>
		<ps>20</ps>
		<pa>0</pa>
		<pe>80</pe>
		<pi>0</pi>
	</it>
	<it>
		<idit>38</idit>
		<tid>1</tid>
		<name>warlord helmet</name>
		<s>2</s>
		<a>0</a>
		<e>2</e>
		<i>0</i>
		<ps>0</ps>
		<pa>0</pa>
		<pe>0</pe>
		<pi>0</pi>
	</it>
	<it>
		<idit>39</idit>
		<tid>2</tid>
		<name>warlord armour</name>
		<s>2</s>
		<a>0</a>
		<e>2</e>
		<i>0</i>
		<ps>0</ps>
		<pa>0</pa>
		<pe>0</pe>
		<pi>0</pi>
	</it>
	<it>
		<idit>40</idit>
		<tid>3</tid>
		<name>warlord leggins</name>
		<s>2</s>
		<a>0</a>
		<e>2</e>
		<i>0</i>
		<ps>0</ps>
		<pa>0</pa>
		<pe>0</pe>
		<pi>0</pi>
	</it>
	<it>
		<idit>41</idit>
		<tid>4</tid>
		<name>warlord boots</name>
		<s>2</s>
		<a>0</a>
		<e>2</e>
		<i>0</i>
		<ps>0</ps>
		<pa>0</pa>
		<pe>0</pe>
		<pi>0</pi>
	</it>
	<it>
		<idit>42</idit>
		<tid>5</tid>
		<name>warlord shield</name>
		<s>2</s>
		<a>0</a>
		<e>2</e>
		<i>0</i>
		<ps>0</ps>
		<pa>0</pa>
		<pe>0</pe>
		<pi>0</pi>
	</it>
	<it>
		<idit>43</idit>
		<tid>12</tid>
		<name>long sword</name>
		<s>3</s>
		<a>1</a>
		<e>0</e>
		<i>0</i>
		<ps>90</ps>
		<pa>20</pa>
		<pe>0</pe>
		<pi>0</pi>
	</it>
	<it>
		<idit>44</idit>
		<tid>1</tid>
		<name>knight helmet</name>
		<s>3</s>
		<a>1</a>
		<e>0</e>
		<i>0</i>
		<ps>0</ps>
		<pa>0</pa>
		<pe>0</pe>
		<pi>0</pi>
	</it>
	<it>
		<idit>45</idit>
		<tid>2</tid>
		<name>knight aromur</name>
		<s>3</s>
		<a>1</a>
		<e>0</e>
		<i>0</i>
		<ps>0</ps>
		<pa>0</pa>
		<pe>0</pe>
		<pi>0</pi>
	</it>
	<it>
		<idit>46</idit>
		<tid>3</tid>
		<name>knight leggins </name>
		<s>3</s>
		<a>1</a>
		<e>0</e>
		<i>0</i>
		<ps>0</ps>
		<pa>0</pa>
		<pe>0</pe>
		<pi>0</pi>
	</it>
	<it>
		<idit>47</idit>
		<tid>4</tid>
		<name>knight boots</name>
		<s>3</s>
		<a>1</a>
		<e>0</e>
		<i>0</i>
		<ps>0</ps>
		<pa>0</pa>
		<pe>0</pe>
		<pi>0</pi>
	</it>
	<it>
		<idit>48</idit>
		<tid>5</tid>
		<name>knight shield</name>
		<s>3</s>
		<a>1</a>
		<e>0</e>
		<i>0</i>
		<ps>0</ps>
		<pa>0</pa>
		<pe>0</pe>
		<pi>0</pi>
	</it>
	<it>
		<idit>49</idit>
		<tid>13</tid>
		<name>hammer</name>
		<s>1</s>
		<a>0</a>
		<e>3</e>
		<i>0</i>
		<ps>10</ps>
		<pa>0</pa>
		<pe>90</pe>
		<pi>0</pi>
	</it>
	<it>
		<idit>50</idit>
		<tid>1</tid>
		<name>warrior helmet</name>
		<s>1</s>
		<a>0</a>
		<e>3</e>
		<i>0</i>
		<ps>0</ps>
		<pa>0</pa>
		<pe>0</pe>
		<pi>0</pi>
	</it>
	<it>
		<idit>51</idit>
		<tid>2</tid>
		<name>warrior armour</name>
		<s>1</s>
		<a>0</a>
		<e>3</e>
		<i>0</i>
		<ps>0</ps>
		<pa>0</pa>
		<pe>0</pe>
		<pi>0</pi>
	</it>
	<it>
		<idit>52</idit>
		<tid>3</tid>
		<name>warrior leggins</name>
		<s>1</s>
		<a>0</a>
		<e>3</e>
		<i>0</i>
		<ps>0</ps>
		<pa>0</pa>
		<pe>0</pe>
		<pi>0</pi>
	</it>
	<it>
		<idit>53</idit>
		<tid>4</tid>
		<name>warrior boots </name>
		<s>1</s>
		<a>0</a>
		<e>3</e>
		<i>0</i>
		<ps>0</ps>
		<pa>0</pa>
		<pe>0</pe>
		<pi>0</pi>
	</it>
	<it>
		<idit>54</idit>
		<tid>5</tid>
		<name>warrior helmet</name>
		<s>1</s>
		<a>0</a>
		<e>3</e>
		<i>0</i>
		<ps>0</ps>
		<pa>0</pa>
		<pe>0</pe>
		<pi>0</pi>
	</it>
	<it>
		<idit>55</idit>
		<tid>14</tid>
		<name>skewer</name>
		<s>2</s>
		<a>2</a>
		<e>0</e>
		<i>0</i>
		<ps>70</ps>
		<pa>60</pa>
		<pe>0</pe>
		<pi>0</pi>
	</it>
	<it>
		<idit>56</idit>
		<tid>1</tid>
		<name>swordsman helmet</name>
		<s>2</s>
		<a>2</a>
		<e>0</e>
		<i>0</i>
		<ps>0</ps>
		<pa>0</pa>
		<pe>0</pe>
		<pi>0</pi>
	</it>
	<it>
		<idit>57</idit>
		<tid>2</tid>
		<name>swordsman armour</name>
		<s>2</s>
		<a>2</a>
		<e>0</e>
		<i>0</i>
		<ps>0</ps>
		<pa>0</pa>
		<pe>0</pe>
		<pi>0</pi>
	</it>
	<it>
		<idit>58</idit>
		<tid>3</tid>
		<name>swordsman leggins</name>
		<s>2</s>
		<a>2</a>
		<e>0</e>
		<i>0</i>
		<ps>0</ps>
		<pa>0</pa>
		<pe>0</pe>
		<pi>0</pi>
	</it>
	<it>
		<idit>59</idit>
		<tid>4</tid>
		<name>swordsman boots</name>
		<s>2</s>
		<a>2</a>
		<e>0</e>
		<i>0</i>
		<ps>0</ps>
		<pa>0</pa>
		<pe>0</pe>
		<pi>0</pi>
	</it>
	<it>
		<idit>60</idit>
		<tid>5</tid>
		<name>swordsman shield</name>
		<s>2</s>
		<a>2</a>
		<e>0</e>
		<i>0</i>
		<ps>0</ps>
		<pa>0</pa>
		<pe>0</pe>
		<pi>0</pi>
	</it>
</items>